{"data": [{"entities": {"urls": [{"start": 219, "end": 242, "url": "https://t.co/UtMHeD6WET", "expanded_url": "https://mesonet.agron.iastate.edu/lsr/#JAX/201907042140/201907042140", "display_url": "mesonet.agron.iastate.edu/lsr/#JAX/20190\u2026"}]}, "author_id": "34934509", "public_metrics": {"retweet_count": 0, "reply_count": 0, "like_count": 0, "quote_count": 0}, "text": "At 5:40 PM EDT, 4 S Newberry [Alachua Co, FL] TRAINED SPOTTER reports TSTM WND DMG. TRAINED SPOTTER REPORTED LARGE TREE LIMBS DOWNED AND PANELS OF FENCING FLUNG BY STRONG WIND GUSTS. TIME OF DAMAGE BASED ON RADAR DATA. https://t.co/UtMHeD6WET", "reply_settings": "everyone", "geo": {"coordinates": {"type": "Point", "coordinates": [-82.62, 29.58]}, "place_id": "4ec01c9dbc693497"}, "source": "iembot", "id": "1146906202682490880", "lang": "en", "created_at": "2019-07-04T22:18:41.000Z", "conversation_id": "1146906202682490880", "possibly_sensitive": false}], "includes": {"users": [{"id": "34934509", "name": "IEMBot JAX", "username": "iembot_jax"}], "places": [{"country": "United States", "name": "Florida", "id": "4ec01c9dbc693497", "geo": {"type": "Feature", "bbox": [-87.634643, 24.396308, -79.974307, 31.001056], "properties": {}}, "full_name": "Florida, USA", "place_type": "admin", "country_code": "US"}]}, "meta": {"newest_id": "1146906202682490880", "oldest_id": "1146906202682490880", "result_count": 1}}